{
    "\u0428\u0442\u043e\u0440\u043c\u0433\u0440\u0430\u0434": [
        {
            "coordinates": "[410, 320]",
            "units": [
                {
                    "unit_image": "files/army/giperion/pretorian.jpg",
                    "unit_name": "\u041f\u0440\u0435\u0442\u043e\u0440\u0438\u0430\u043d\u0446\u044b",
                    "unit_count": 3687,
                    "units_stats": {
                        "\u0423\u0440\u043e\u043d": 720000,
                        "\u0417\u0430\u0449\u0438\u0442\u0430": 360000,
                        "\u0416\u0438\u0432\u0443\u0447\u0435\u0441\u0442\u044c": 480000,
                        "\u041a\u043b\u0430\u0441\u0441 \u044e\u043d\u0438\u0442\u0430": "1"
                    }
                },
                {
                    "unit_image": "files/army/giperion/BM390.jpg",
                    "unit_name": "\u0426\u0435\u0437\u0430\u0440\u044c",
                    "unit_count": 6452,
                    "units_stats": {
                        "\u0423\u0440\u043e\u043d": 9170000,
                        "\u0417\u0430\u0449\u0438\u0442\u0430": 665000,
                        "\u0416\u0438\u0432\u0443\u0447\u0435\u0441\u0442\u044c": 840000,
                        "\u041a\u043b\u0430\u0441\u0441 \u044e\u043d\u0438\u0442\u0430": "3"
                    }
                },
                {
                    "unit_image": "files/army/giperion/varvar.jpg",
                    "unit_name": "\u0426\u0435\u043d\u0442\u0443\u0440\u0438\u043e\u043d",
                    "unit_count": 3226,
                    "units_stats": {
                        "\u0423\u0440\u043e\u043d": 2275000,
                        "\u0417\u0430\u0449\u0438\u0442\u0430": 1400000,
                        "\u0416\u0438\u0432\u0443\u0447\u0435\u0441\u0442\u044c": 1890000,
                        "\u041a\u043b\u0430\u0441\u0441 \u044e\u043d\u0438\u0442\u0430": "2"
                    }
                },
                {
                    "unit_image": "files/army/giperion/valkirya.jpg",
                    "unit_name": "\u0412\u0430\u043b\u044c\u043a\u0438\u0440\u0438\u044f",
                    "unit_count": 1382,
                    "units_stats": {
                        "\u0423\u0440\u043e\u043d": 2385000,
                        "\u0417\u0430\u0449\u0438\u0442\u0430": 165000,
                        "\u0416\u0438\u0432\u0443\u0447\u0435\u0441\u0442\u044c": 495000,
                        "\u041a\u043b\u0430\u0441\u0441 \u044e\u043d\u0438\u0442\u0430": "4"
                    }
                },
                {
                    "unit_image": "files/army/giperion/CPS-12.jpg",
                    "unit_name": "HPAAL",
                    "unit_count": 2765,
                    "units_stats": {
                        "\u0423\u0440\u043e\u043d": 240000,
                        "\u0417\u0430\u0449\u0438\u0442\u0430": 4650000,
                        "\u0416\u0438\u0432\u0443\u0447\u0435\u0441\u0442\u044c": 660000,
                        "\u041a\u043b\u0430\u0441\u0441 \u044e\u043d\u0438\u0442\u0430": "3"
                    }
                },
                {
                    "unit_image": "files/army/giperion/k-17.jpg",
                    "unit_name": "\u041a-17",
                    "unit_count": 55,
                    "units_stats": {
                        "\u0423\u0440\u043e\u043d": 5016000,
                        "\u0417\u0430\u0449\u0438\u0442\u0430": 1722000,
                        "\u0416\u0438\u0432\u0443\u0447\u0435\u0441\u0442\u044c": 2369400,
                        "\u041a\u043b\u0430\u0441\u0441 \u044e\u043d\u0438\u0442\u0430": "4"
                    }
                }
            ]
        }
    ]
}