{
    "Аль-Шахара": {
        "Здания": {
            "Больница": 50,
            "Фабрика": 100
        },
        "Координаты": [
            820,
            160
        ]
    },
    "Тамир": {
        "Здания": {
            "Больница": 45,
            "Фабрика": 90
        },
        "Координаты": [
            940,
            280
        ]
    },
    "Рамшад": {
        "Здания": {
            "Больница": 46,
            "Фабрика": 92
        },
        "Координаты": [
            1000,
            480
        ]
    },
    "Эркан": {
        "Здания": {
            "Больница": 45,
            "Фабрика": 90
        },
        "Координаты": [
            1020,
            100
        ]
    }
}